LICENSE
README.md
setup.py
yubiconvert/__init__.py
yubiconvert/yubiconvert.py
yubiconvert.egg-info/PKG-INFO
yubiconvert.egg-info/SOURCES.txt
yubiconvert.egg-info/dependency_links.txt
yubiconvert.egg-info/requires.txt
yubiconvert.egg-info/top_level.txt