Metadata-Version: 2.1
Name: yubiconvert
Version: 1.0.1
Summary: Python module that can convert numeric words to their numerical form effortlessly
Home-page: https://github.com/Yubi2Community/yubiconvert
Author: Yubi Data Science Team
Author-email: data@go-yubi.com
License: MIT
Keywords: numbers,convert,words,indian,currency
Platform: UNKNOWN
Classifier: Intended Audience :: Developers
Classifier: Programming Language :: Python
